[
    {
      "titulo": "Grande Nuvem de Magalhães",
      "fonte": "SpaceApp",
      "path": "/imagens/galeria/foto-1.png",
      "id": "1",
      "tagId": 2
    },
    {
      "titulo": "Via Láctea",
      "fonte": "SpaceApp",
      "path": "/imagens/galeria/foto-2.png",
      "id": "2",
      "tagId": 2
    },
    {
      "titulo": "Lua: quarto minguante",
      "fonte": "SpaceApp",
      "path": "/imagens/galeria/foto-3.png",
      "id": "3",
      "tagId": 3
    },
    {
      "titulo": "Galáxia de Andrómeda",
      "fonte": "SpaceApp",
      "path": "/imagens/galeria/foto-4.png",
      "id": "4",
      "tagId": 2
    },
    {
      "titulo": "Estrela Pistola",
      "fonte": "SpaceApp",
      "path": "/imagens/galeria/foto-5.png",
      "id": "5",
      "tagId": 1
    },
    {
      "titulo": "Nebulosa",
      "fonte": "SpaceApp",
      "path": "/imagens/galeria/foto-6.png",
      "id": "6",
      "tagId": 4
    },
    {
      "titulo": "Galáxia de Andrómeda",
      "fonte": "SpaceApp",
      "path": "/imagens/galeria/foto-7.png",
      "id": "7",
      "tagId": 2
    },
    {
      "titulo": "Nebulosa",
      "fonte": "SpaceApp",
      "path": "/imagens/galeria/foto-8.png",
      "id": "8",
      "tagId": 4
    },
    {
      "titulo": "Céu estrelado",
      "fonte": "SpaceApp",
      "path": "/imagens/galeria/foto-9.png",
      "id": "9",
      "tagId": 1
    },
    {
      "titulo": "Estrela",
      "fonte": "SpaceApp",
      "path": "/imagens/galeria/foto-10.png",
      "id": "10",
      "tagId": 1
    },
    {
      "titulo": "Lua Cheia",
      "fonte": "SpaceApp",
      "path": "/imagens/galeria/foto-11.png",
      "id": "11",
      "tagId": 3
    },
    {
      "titulo": "Galáxias",
      "fonte": "SpaceApp",
      "path": "/imagens/galeria/foto-12.png",
      "id": "12",
      "tagId": 2
    }
    
  ]